grafito/__init__.py
grafito/database.py
grafito/exceptions.py
grafito/filters.py
grafito/models.py
grafito/query.py
grafito/schema.py
grafito/cypher/__init__.py
grafito/cypher/ast_nodes.py
grafito/cypher/evaluator.py
grafito/cypher/exceptions.py
grafito/cypher/executor.py
grafito/cypher/lexer.py
grafito/cypher/parser.py
grafito/cypher/tokens.py
grafito/cypher/utils.py
grafito/embedding_functions/__init__.py
grafito/embedding_functions/amazon_bedrock.py
grafito/embedding_functions/base.py
grafito/embedding_functions/cohere.py
grafito/embedding_functions/google_genai.py
grafito/embedding_functions/huggingface.py
grafito/embedding_functions/jina.py
grafito/embedding_functions/mistral.py
grafito/embedding_functions/ollama.py
grafito/embedding_functions/openai.py
grafito/embedding_functions/sentence_transformer.py
grafito/embedding_functions/tfhub.py
grafito/embedding_functions/together_ai.py
grafito/embedding_functions/voyageai.py
grafito/importers/__init__.py
grafito/importers/neo4j_dump.py
grafito/indexers/__init__.py
grafito/indexers/annoy.py
grafito/indexers/base.py
grafito/indexers/bruteforce.py
grafito/indexers/faiss.py
grafito/indexers/hnswlib.py
grafito/indexers/leann.py
grafito/indexers/usearch.py
grafito/indexers/voyager.py
grafito/integrations/__init__.py
grafito/integrations/rdf.py
grafito/integrations/viz.py
grafito/text_index/__init__.py
grafito/text_index/base.py
grafito/text_index/bm25s.py
grafito/text_index/sqlite_fts.py
grafito/vector_index/__init__.py
grafito/vector_index/annoy.py
grafito/vector_index/base.py
grafito/vector_index/bruteforce.py
grafito/vector_index/faiss.py
grafito/vector_index/hnswlib.py
grafito/vector_index/leann.py
grafito/vector_index/usearch.py
grafito/vector_index/voyager.py
grafito-0.1.2.dist-info/METADATA
grafito-0.1.2.dist-info/WHEEL
grafito-0.1.2.dist-info/licenses/LICENSE
grafito-0.1.2.dist-info/RECORD
