Metadata-Version: 2.4
Name: grafito
Version: 0.1.2
Summary: SQLite-based Property Graph Database
License-File: LICENSE
Requires-Python: >=3.11
Requires-Dist: networkx>=3.6.1
Requires-Dist: orjson>=3.11.5
Requires-Dist: zstandard>=0.23.0
Provides-Extra: all
Requires-Dist: annoy>=1.17.3; extra == 'all'
Requires-Dist: bm25s>=0.2.2; extra == 'all'
Requires-Dist: faiss-cpu>=1.13.2; extra == 'all'
Requires-Dist: hnswlib>=0.8.0; extra == 'all'
Requires-Dist: leann>=0.3.6; extra == 'all'
Requires-Dist: pyvis>=0.3.2; extra == 'all'
Requires-Dist: rdflib>=7.0.0; extra == 'all'
Requires-Dist: usearch>=2.0.0; extra == 'all'
Requires-Dist: voyager>=2.0.0; extra == 'all'
Provides-Extra: annoy
Requires-Dist: annoy>=1.17.3; extra == 'annoy'
Provides-Extra: bm25s
Requires-Dist: bm25s>=0.2.2; extra == 'bm25s'
Provides-Extra: dev
Requires-Dist: pytest-cov>=4.1.0; extra == 'dev'
Requires-Dist: pytest>=8.0.0; extra == 'dev'
Provides-Extra: docs
Requires-Dist: mkdocs-material>=9.5.0; extra == 'docs'
Requires-Dist: mkdocstrings[python]>=0.24.0; extra == 'docs'
Provides-Extra: faiss
Requires-Dist: faiss-cpu>=1.13.2; extra == 'faiss'
Provides-Extra: hnswlib
Requires-Dist: hnswlib>=0.8.0; extra == 'hnswlib'
Provides-Extra: leann
Requires-Dist: leann>=0.3.6; extra == 'leann'
Provides-Extra: rdf
Requires-Dist: rdflib>=7.0.0; extra == 'rdf'
Provides-Extra: usearch
Requires-Dist: usearch>=2.0.0; extra == 'usearch'
Provides-Extra: viz
Requires-Dist: pyvis>=0.3.2; extra == 'viz'
Provides-Extra: voyager
Requires-Dist: voyager>=2.0.0; extra == 'voyager'
